irmetrics/__init__.py
irmetrics/coverage.py
irmetrics/flat.py
irmetrics/io.py
irmetrics/relevance.py
irmetrics/topk.py
ir_metrics-0.1.6.dist-info/LICENSE.md
ir_metrics-0.1.6.dist-info/METADATA
ir_metrics-0.1.6.dist-info/WHEEL
ir_metrics-0.1.6.dist-info/top_level.txt
ir_metrics-0.1.6.dist-info/RECORD
