Metadata-Version: 2.1
Name: ir-metrics
Version: 0.1.6
Summary: The most common information retrieval (IR) metrics
Home-page: https://github.com/kqf/ir-metrics
License: UNKNOWN
Platform: UNKNOWN
Classifier: License :: OSI Approved :: MIT License
Classifier: Operating System :: OS Independent
Classifier: Intended Audience :: Science/Research
Classifier: Intended Audience :: Developers
Classifier: Programming Language :: Python :: 3
Classifier: Programming Language :: Python :: 3.6
Classifier: Programming Language :: Python :: 3.7
Classifier: Programming Language :: Python :: 3.8
Classifier: Programming Language :: Python :: 3.9
Classifier: Programming Language :: Python :: 3 :: Only
Classifier: Topic :: Software Development
Classifier: Topic :: Scientific/Engineering
Requires-Python: >=3.6, <4
Requires-Dist: numpy
Provides-Extra: pandas
Requires-Dist: pandas ; extra == 'pandas'
